CHANGELOG.txt
LICENCE.txt
MANIFEST.in
README.txt
setup.py
ylibrary/__init__.py
ylibrary.egg-info/PKG-INFO
ylibrary.egg-info/SOURCES.txt
ylibrary.egg-info/dependency_links.txt
ylibrary.egg-info/requires.txt
ylibrary.egg-info/top_level.txt